Metadata-Version: 1.1
Name: folha-de-frequencia
Version: 0.0.1
Summary: Classes para geração de um folha de frequência
Home-page: https://github.com/gimoteco/folha-de-frequencia
Author: Guilherme Barbosa Ferreira
Author-email: gimoteco@gmail.com
License: UNKNOWN
Platform: UNKNOWN
Classifier: Programming Language :: Python :: 3
Classifier: License :: OSI Approved :: MIT License
Classifier: Operating System :: OS Independent
